projkit/__init__.py
projkit/camops.py
projkit/imutils.py
projkit/pyutils.py
projkit-0.1.3.dist-info/LICENSE
projkit-0.1.3.dist-info/METADATA
projkit-0.1.3.dist-info/WHEEL
projkit-0.1.3.dist-info/top_level.txt
projkit-0.1.3.dist-info/RECORD
