Metadata-Version: 2.1
Name: projkit
Version: 0.1.3
Summary: Library designed to simplify camera projection tasks and calculations, particularly when working with image predictions and 3D point cloud data. This library provides functions to effectively incorporate point cloud data with image predictions.
Home-page: https://github.com/fuzailpalnak/projkit
Author: Fuzail Palnak
Author-email: fuzailpalnak@gmail.com
Keywords: Camera Projections,3d Projections,2d projections,point cloud
Classifier: Programming Language :: Python :: 3
Classifier: Topic :: Software Development :: Libraries
Classifier: Topic :: Software Development :: Libraries :: Python Modules
Classifier: Intended Audience :: Developers
Classifier: Operating System :: OS Independent
Requires-Python: >=3.6
License-File: LICENSE
